swajime/SwaANSI.py
swajime/__init__.py
tests/__init__.py
tests/test_swaansi.py
SwaANSI_pkg_swajime-0.1.1.dist-info/LICENSE
SwaANSI_pkg_swajime-0.1.1.dist-info/METADATA
SwaANSI_pkg_swajime-0.1.1.dist-info/WHEEL
SwaANSI_pkg_swajime-0.1.1.dist-info/top_level.txt
SwaANSI_pkg_swajime-0.1.1.dist-info/RECORD
